ipycanvas/__init__.py
ipycanvas/_frontend.py
ipycanvas/_version.py
ipycanvas/call_repeated.py
ipycanvas/canvas.py
ipycanvas/compat.py
ipycanvas/utils.py
ipycanvas/labextension/package.json
ipycanvas/labextension/static/122.798ec8c3ecacb9105364.js
ipycanvas/labextension/static/287.1f872f30ec5ffd00c31b.js
ipycanvas/labextension/static/287.1f872f30ec5ffd00c31b.js.LICENSE.txt
ipycanvas/labextension/static/509.94b5c681c7259af8ec75.js
ipycanvas/labextension/static/796.c9dcb80a4759cbd09bbb.js
ipycanvas/labextension/static/819.badc5d48ed3502f8d9eb.js
ipycanvas/labextension/static/remoteEntry.fb45db9d3f32bd4bc57a.js
ipycanvas/labextension/static/style.js
ipycanvas/labextension/static/third-party-licenses.json
ipycanvas/nbextension/static/extension.js
ipycanvas/nbextension/static/index.js
ipycanvas/nbextension/static/index.js.LICENSE.txt
ipycanvas/offscreen_canvas/__init__.py
ipycanvas/offscreen_canvas/offscreen_canvas.py
ipycanvas/offscreen_canvas/offscreen_canvas_core.py
ipycanvas/offscreen_canvas/js/init.js
ipycanvas-0.14.1.data/data/share/jupyter/labextensions/ipycanvas/package.json
ipycanvas-0.14.1.data/data/share/jupyter/labextensions/ipycanvas/static/122.798ec8c3ecacb9105364.js
ipycanvas-0.14.1.data/data/share/jupyter/labextensions/ipycanvas/static/287.1f872f30ec5ffd00c31b.js
ipycanvas-0.14.1.data/data/share/jupyter/labextensions/ipycanvas/static/287.1f872f30ec5ffd00c31b.js.LICENSE.txt
ipycanvas-0.14.1.data/data/share/jupyter/labextensions/ipycanvas/static/509.94b5c681c7259af8ec75.js
ipycanvas-0.14.1.data/data/share/jupyter/labextensions/ipycanvas/static/796.c9dcb80a4759cbd09bbb.js
ipycanvas-0.14.1.data/data/share/jupyter/labextensions/ipycanvas/static/819.badc5d48ed3502f8d9eb.js
ipycanvas-0.14.1.data/data/share/jupyter/labextensions/ipycanvas/static/remoteEntry.fb45db9d3f32bd4bc57a.js
ipycanvas-0.14.1.data/data/share/jupyter/labextensions/ipycanvas/static/style.js
ipycanvas-0.14.1.data/data/share/jupyter/labextensions/ipycanvas/static/third-party-licenses.json
ipycanvas-0.14.1.dist-info/METADATA
ipycanvas-0.14.1.dist-info/WHEEL
ipycanvas-0.14.1.dist-info/licenses/LICENSE.txt
ipycanvas-0.14.1.dist-info/RECORD
