Metadata-Version: 2.4
Name: ipycanvas
Version: 0.14.1
Summary: Interactive widgets library exposing the browser's Canvas API
Project-URL: Homepage, https://github.com/jupyter-widgets-contrib/ipycanvas
Author-email: Martin Renou <martin.renou@gmail.com>
License: Copyright (c) 2019 Martin Renou
License-File: LICENSE.txt
Keywords: IPython,Jupyter,Widgets
Classifier: Framework :: Jupyter
Classifier: Intended Audience :: Developers
Classifier: Intended Audience :: Science/Research
Classifier: License :: OSI Approved :: BSD License
Classifier: Programming Language :: Python
Classifier: Programming Language :: Python :: 3
Classifier: Programming Language :: Python :: 3.8
Classifier: Programming Language :: Python :: 3.9
Classifier: Programming Language :: Python :: 3.10
Classifier: Programming Language :: Python :: 3.11
Classifier: Programming Language :: Python :: 3.12
Requires-Dist: ipywidgets<9,>=7.6.0
Requires-Dist: numpy
Requires-Dist: pillow>=6.0
